dotmix/__init__.py
dotmix/appearance.py
dotmix/cli/__init__.py
dotmix/cli/cli.py
dotmix/cli/completion.py
dotmix/cli/py.typed
dotmix/cli/utils.py
dotmix/colorscheme.py
dotmix/colorutils.py
dotmix/config.py
dotmix/data.py
dotmix/fileset.py
dotmix/py.typed
dotmix/runner.py
dotmix/typography.py
dotmix/utils.py
dotmix/vendor/__init__.py
dotmix/vendor/colp.py
dotmix-0.3.0.dist-info/entry_points.txt
dotmix-0.3.0.dist-info/WHEEL
dotmix-0.3.0.dist-info/METADATA
dotmix-0.3.0.dist-info/RECORD
